imgcv/__init__.py
imgcv/common.py
imgcv/connectivity/__init__.py
imgcv/connectivity/connected_components.py
imgcv/fftpack/__init__.py
imgcv/fftpack/fft.py
imgcv/filters/__init__.py
imgcv/filters/freq_domain.py
imgcv/filters/linear.py
imgcv/filters/non_linear.py
imgcv/filters/utils.py
imgcv/histogram/__init__.py
imgcv/histogram/histogram_equalization.py
imgcv/histogram/matching.py
imgcv/quantization/__init__.py
imgcv/quantization/reduce_gray_levels.py
imgcv/quantization/to_binary.py
imgcv/transformations/__init__.py
imgcv/transformations/gamma.py
imgcv/transformations/logarithmic.py
imgcv/transformations/negative.py
imgcv-0.10.0.dist-info/LICENSE
imgcv-0.10.0.dist-info/METADATA
imgcv-0.10.0.dist-info/WHEEL
imgcv-0.10.0.dist-info/RECORD
